{"is_source_file": true, "file_id": 16, "git_revision": "", "state": 1, "description": "", "external_files": [], "external_methods": [], "published": [], "classes": [], "methods": [], "calls": [], "search-terms": [], "ctags": [{"_type": "tag", "name": "QuestionCard", "path": "/home/kavia/workspace/code-generation/classroom-quiz-board-50758-50769/quiz_frontend_tv/src/components/QuestionCard.js", "pattern": "/^export default function QuestionCard({ title, body, answer, answerRevealed }) {$/", "language": "JavaScript", "kind": "function", "signature": "({ title, body, answer, answerRevealed })"}], "format": "JavaScript", "hash": "713b42fb9346ba80aa87777e8b252eb9", "format-version": 4, "code-base-name": "quiz_frontend_tv", "filename": "quiz_frontend_tv/src/components/QuestionCard.js", "knowledge_revision": 30}